{"author": "http://www.nytimes.com/by/alan-feuer, http://www.nytimes.com/by/benjamin-weiser", "title": "Judge Suggests Review of Cohen Documents Is Moving Too Slowly", "description": "A federal judge for Mr. Cohen were given a June 15 deadline to review the documents seized from his office, apartment and hotel room.", "url": "https://www.nytimes.com/2018/05/30/nyregion/trump-michael-cohen-stormy-daniels.html", "urlToImage": "https://static01.nyt.com/images/2018/05/31/nyregion/31cohen2/31cohen2-facebookJumbo.jpg", "publishedAt": "2018-05-30T17:21:31.538Z", "clasificare": {"general": 0.15947572257134987, "technology": 0.2038521413515914, "sports": 0.1825054941072266, "business": 0.2517114351438094, "entertainment": 0.13843955849284587, "science": 0.19879495284166526}}